chessf/__init__.py
chessf/analysis.py
chessf/cli.py
chessf/core.py
chessf-0.1.1.dist-info/LICENSE
chessf-0.1.1.dist-info/METADATA
chessf-0.1.1.dist-info/WHEEL
chessf-0.1.1.dist-info/entry_points.txt
chessf-0.1.1.dist-info/RECORD
