Metadata-Version: 2.3
Name: chessf
Version: 0.1.1
Summary: 
Author: GPT-Design
Author-email: gpt.design500@gmail.com
Requires-Python: >=3.12,<3.14
Classifier: Programming Language :: Python :: 3
Classifier: Programming Language :: Python :: 3.12
Classifier: Programming Language :: Python :: 3.13
Provides-Extra: gpu
Requires-Dist: matplotlib (>=3.10.1,<4.0.0)
Requires-Dist: mpmath (>=1.3.0,<2.0.0)
Requires-Dist: numpy (>=2.2.5,<3.0.0)
Requires-Dist: pandas (>=2.2.3,<3.0.0)
Requires-Dist: pyarrow (>=20.0.0,<21.0.0)
Requires-Dist: python-chess (>=1.999,<2.0)
Requires-Dist: rich (>=14.0.0,<15.0.0)
Requires-Dist: scipy (>=1.15.2,<2.0.0)
Requires-Dist: typer (>=0.15.3,<0.16.0)
